flask_pydantic_api/__init__.py
flask_pydantic_api/api_wrapper.py
flask_pydantic_api/apidocs_views.py
flask_pydantic_api/openapi.py
flask_pydantic_api/py.typed
flask_pydantic_api/utils.py
flask_pydantic_api/templates/rapidoc.html
flask_pydantic_api-1.7.0.dist-info/licenses/LICENSE
flask_pydantic_api-1.7.0.dist-info/METADATA
flask_pydantic_api-1.7.0.dist-info/WHEEL
flask_pydantic_api-1.7.0.dist-info/top_level.txt
flask_pydantic_api-1.7.0.dist-info/RECORD
