Metadata-Version: 2.4
Name: flask-pydantic-api
Version: 1.7.0
Summary: Pydantic based API support for Flask
Home-page: https://github.com/adamsussman/flask-pydantic-api
Author: Adam Sussman
Author-email: adam.sussman@gmail.com
License: MIT
Classifier: Development Status :: 5 - Production/Stable
Classifier: Framework :: Pydantic
Classifier: Framework :: Flask
Classifier: Intended Audience :: Developers
Classifier: License :: OSI Approved :: MIT License
Classifier: Operating System :: OS Independent
Classifier: Programming Language :: Python :: 3 :: Only
Classifier: Topic :: Software Development :: Libraries :: Python Modules
Classifier: Topic :: Internet
License-File: LICENSE
Requires-Dist: asgiref>=3.6
Requires-Dist: flask>=2.2
Requires-Dist: pydantic>=2.5
Provides-Extra: serializer
Requires-Dist: pydantic_enhanced_serializer>=2; extra == "serializer"
Provides-Extra: test
Requires-Dist: pytest; extra == "test"
Requires-Dist: pytest-cov; extra == "test"
Requires-Dist: pytest_mock; extra == "test"
Provides-Extra: dev
Requires-Dist: mypy; extra == "dev"
Requires-Dist: black; extra == "dev"
Requires-Dist: ipdb; extra == "dev"
Requires-Dist: isort; extra == "dev"
Requires-Dist: flake8; extra == "dev"
Requires-Dist: flake8-bugbear; extra == "dev"
Requires-Dist: flake8-debugger; extra == "dev"
Requires-Dist: types-setuptools; extra == "dev"
Dynamic: license-file
